<?xml version="1.0" encoding="UTF-8"?>
<LanguageData>
  
  <!-- EN: bandwidth cost -->
  <BandwidthCost.label>頻寬佔用</BandwidthCost.label>
  <!-- EN: How much bandwidth this mech consumes when under mechanitor control. -->
  <BandwidthCost.description>若在御機使的操控下，這台機械族會佔用多少頻寬。</BandwidthCost.description>
  
  <!-- EN: cancer rate factor -->
  <CancerRate.label>罹癌率</CancerRate.label>
  <!-- EN: A multiplier on how likely this person is to develop cancer in any given time frame. -->
  <CancerRate.description>這名角色在任何時間中，罹患癌症的倍率。</CancerRate.description>
  
  <!-- EN: control taking time -->
  <ControlTakingTime.label>操控耗時</ControlTakingTime.label>
  <!-- EN: How many seconds it will take for a mechanitor to take control of this mech. -->
  <ControlTakingTime.description>御機使操控這台機械族所需的時間。</ControlTakingTime.description>
  <!-- EN: {0}s -->
  <ControlTakingTime.formatString>{0}秒</ControlTakingTime.formatString>
  
  <!-- EN: fertility -->
  <Fertility.label>生育能力</Fertility.label>
  <!-- EN: Fertility affects the chance of a pregnancy occurring. Pregnancy chance is dependent on the fertility of both partners. This also affects the chance of successfully implanting an embryo in a surrogate. -->
  <Fertility.description>生育能力影響懷孕的機率。懷孕機率取決於雙方的生育能力。這也會影響代孕植入胚胎時的成功率。</Fertility.description>
  
  <!-- EN: growth vat occupant speed -->
  <GrowthVatOccupantSpeed.label>發育速度</GrowthVatOccupantSpeed.label>
  <!-- EN: A multiplier on how quickly this person will grow when in a growth vat. -->
  <GrowthVatOccupantSpeed.description>發育艙中的人成長速度的倍率。</GrowthVatOccupantSpeed.description>
  
  <!-- EN: hemogen gain multiplier -->
  <HemogenGainFactor.label>血原獲取倍率</HemogenGainFactor.label>
  <!-- EN: A multiplier on the amount of hemogen gained. -->
  <HemogenGainFactor.description>獲取血原數量的倍率。</HemogenGainFactor.description>
  
  <!-- EN: learning rate factor -->
  <LearningRateFactor.label>學習速度</LearningRateFactor.label>
  <!-- EN: A multiplier on how quickly a child's learning need is fulfilled by learning activities. -->
  <LearningRateFactor.description>兒童從學習活動中滿足學習需求的速度。</LearningRateFactor.description>
  
  <!-- EN: mech bandwidth -->
  <MechBandwidth.label>機械族頻寬</MechBandwidth.label>
  <!-- EN: How much bandwidth a mechanitor has. More bandwidth allows a mechanitor to produce and control more mechs at the same time.\n\nLosing bandwidth means losing control of mechs, leaving them without an overseer. Such mechs can eventually become feral if not re-dominated. -->
  <MechBandwidth.description>御機使擁有的頻寬。更多的頻寬允許御機使製造和操控更多的機械族。\n\n失去頻寬就表示失去對機械族的操控，使它們沒有監督者。如果不重新駕馭，最終會變為失控機械族。</MechBandwidth.description>
  
  <!-- EN: mech control groups -->
  <MechControlGroups.label>機械操控組</MechControlGroups.label>
  <!-- EN: How many control groups this mechanitor can direct independently. Each control group can be given its own separate orders. -->
  <MechControlGroups.description>御機使可以指揮的操控組數量。每個操控組都可設定各別的指令。</MechControlGroups.description>
  
  <!-- EN: repair energy cost -->
  <MechEnergyLossPerHP.label>維修能源消耗</MechEnergyLossPerHP.label>
  <!-- EN: The amount of energy that this mechanoid loses for every 100 damage repaired. -->
  <MechEnergyLossPerHP.description>機械族每修復100傷害所消耗的能源。</MechEnergyLossPerHP.description>
  
  <!-- EN: energy usage multiplier -->
  <MechEnergyUsageFactor.label>能源使用倍率</MechEnergyUsageFactor.label>
  <!-- EN: A multiplier on how fast a mechanoid consumes its energy reserves while operating. -->
  <MechEnergyUsageFactor.description>機械族運作時消耗儲備能源的速度倍率。</MechEnergyUsageFactor.description>
  
  <!-- EN: mech gestation speed -->
  <MechFormingSpeed.label>機械族培養速度</MechFormingSpeed.label>
  <!-- EN: A multiplier on the speed at which this mechanitor can form new mechanoids at a gestator. -->
  <MechFormingSpeed.description>御機使在培養艙形成新機械族的速度倍率。</MechFormingSpeed.description>
  
  <!-- EN: mech remote repair distance -->
  <MechRemoteRepairDistance.label>機械族遙距修復距離</MechRemoteRepairDistance.label>
  <!-- EN: How far away a mech can be during remote repair. -->
  <MechRemoteRepairDistance.description>可以遙距修復離機械族的最遠距離。</MechRemoteRepairDistance.description>
  
  <!-- EN: mech remote shield distance -->
  <MechRemoteShieldDistance.label>機械族遙距護盾距離</MechRemoteShieldDistance.label>
  <!-- EN: The maximum range at which a mechanitor can place a shield on a mechanoid. -->
  <MechRemoteShieldDistance.description>御機使可以在機械族身上放置護盾的最大範圍。</MechRemoteShieldDistance.description>
  
  <!-- EN: mech remote shield energy -->
  <MechRemoteShieldEnergy.label>機械族遙距護盾能源</MechRemoteShieldEnergy.label>
  <!-- EN: The energy a remote shield will have when created by a mechanitor. -->
  <MechRemoteShieldEnergy.description>被御機使放置遙距護盾時所具有的能源。</MechRemoteShieldEnergy.description>
  
  <!-- EN: mech repair speed -->
  <MechRepairSpeed.label>機械族修復速度</MechRepairSpeed.label>
  <!-- EN: A multiplier on how fast a mechanitor can repair mechanoids. -->
  <MechRepairSpeed.description>御機使修復機械族的速度倍率。</MechRepairSpeed.description>
  
  <!-- EN: raw nutrition multiplier -->
  <RawNutritionFactor.label>生食營養倍率</RawNutritionFactor.label>
  <!-- EN: A multiplier on how nutritious raw food is for this person. Note that since meals usually have more nutrition than their raw ingredients, a boost to this stat may only mean the person gets the same nutrition from raw food as if it were cooked. -->
  <RawNutritionFactor.description>吃生食提供的營養倍率。注意，由於烹飪過的食物通常比生食更具有營養，因此提高此屬性可能只代表人們從生食中獲得的營養與烹飪過的食物相同。</RawNutritionFactor.description>
  
  <!-- EN: subcore encoding speed -->
  <SubcoreEncodingSpeed.label>次核心編碼速度</SubcoreEncodingSpeed.label>
  <!-- EN: A multiplier on how fast a mechanitor can create subcores. -->
  <SubcoreEncodingSpeed.description>御機使製造次核心的速度倍率。</SubcoreEncodingSpeed.description>
  
  <!-- EN: wastepacks per recharge -->
  <WastepacksPerRecharge.label>充電廢料量</WastepacksPerRecharge.label>
  <!-- EN: How many toxic wastepacks this mechanoid will generate at a mech recharger when going from 0 to 100% energy. Larger mechanoids will generally create more toxic wastepacks. -->
  <WastepacksPerRecharge.description>當機械族能源由0充至100%時，機械充電站會產生多少的廢料袋。通常較大型的機械族會產生更多的廢料袋。</WastepacksPerRecharge.description>
  <WastepacksPerRecharge.statFactorsExplanationHeader>相關屬性</WastepacksPerRecharge.statFactorsExplanationHeader>
  
</LanguageData>