<?xml version="1.0" encoding="UTF-8"?>
<LanguageData>
  
  <!-- EN: strong -->
  <GauranlenConnection_Strong.label>強烈</GauranlenConnection_Strong.label>
  <!-- EN: We have a special connection with the Gauranlen trees. The trees refocus production easily under our influence, and we are not satisfied unless we have that connection. -->
  <GauranlenConnection_Strong.description>我們與高嵐樹有特別的聯結。在我們的干涉下，它可以輕易改變所出產之物，而若我們未得與樹聯結一起，我們終不滿足。</GauranlenConnection_Strong.description>
  <!-- EN: Gauranlen connection -->
  <GauranlenConnection_Strong.comps.0.thoughtStageDescriptions.0>高嵐樹聯結</GauranlenConnection_Strong.comps.0.thoughtStageDescriptions.0>
  <!-- EN: Want Gauranlen connection (min expectation: Very low) -->
  <GauranlenConnection_Strong.comps.0.thoughtStageDescriptions.1>想與高嵐樹聯結(最低渴求︰非常低)</GauranlenConnection_Strong.comps.0.thoughtStageDescriptions.1>
  <!-- EN: Want Gauranlen connection (min expectation: Low) -->
  <GauranlenConnection_Strong.comps.0.thoughtStageDescriptions.2>想與高嵐樹聯結(最低渴求︰低)</GauranlenConnection_Strong.comps.0.thoughtStageDescriptions.2>
  <!-- EN: Want Gauranlen connection (min expectation: Moderate) -->
  <GauranlenConnection_Strong.comps.0.thoughtStageDescriptions.3>想與高嵐樹聯結(最低渴求︰中)</GauranlenConnection_Strong.comps.0.thoughtStageDescriptions.3>
  <!-- EN: Want Gauranlen connection (min expectation: High) -->
  <GauranlenConnection_Strong.comps.0.thoughtStageDescriptions.4>想與高嵐樹聯結(最低渴求︰高)</GauranlenConnection_Strong.comps.0.thoughtStageDescriptions.4>
  <!-- EN: Want Gauranlen connection (min expectation: Sky high) -->
  <GauranlenConnection_Strong.comps.0.thoughtStageDescriptions.5>想與高嵐樹聯結(最低渴求︰非常高)</GauranlenConnection_Strong.comps.0.thoughtStageDescriptions.5>
  <!-- EN: planted Gauranlen tree -->
  <GauranlenConnection_Strong.comps.1.eventLabel>種下高嵐樹</GauranlenConnection_Strong.comps.1.eventLabel>
  
  <!-- EN: desired -->
  <Trees_Desired.label>渴求</Trees_Desired.label>
  <!-- EN: It's essential to live surrounded by beautiful trees. -->
  <Trees_Desired.description>生活在壯麗大樹之間是生命必不可少的。</Trees_Desired.description>
  <!-- EN: Healthy trees -->
  <Trees_Desired.comps.1.thoughtStageDescriptions.0>健康的樹</Trees_Desired.comps.1.thoughtStageDescriptions.0>
  <!-- EN: Trees disturbed -->
  <Trees_Desired.comps.1.thoughtStageDescriptions.1>樹木受擾了</Trees_Desired.comps.1.thoughtStageDescriptions.1>
  <!-- EN: Trees defaced -->
  <Trees_Desired.comps.1.thoughtStageDescriptions.2>樹木受損了</Trees_Desired.comps.1.thoughtStageDescriptions.2>
  <!-- EN: Trees damaged -->
  <Trees_Desired.comps.1.thoughtStageDescriptions.3>樹木受傷了</Trees_Desired.comps.1.thoughtStageDescriptions.3>
  <!-- EN: Trees harmed -->
  <Trees_Desired.comps.1.thoughtStageDescriptions.4>樹木受破壞了</Trees_Desired.comps.1.thoughtStageDescriptions.4>
  <!-- EN: Trees defiled -->
  <Trees_Desired.comps.1.thoughtStageDescriptions.5>樹木受褻瀆了</Trees_Desired.comps.1.thoughtStageDescriptions.5>
  <!-- EN: Trees wrecked -->
  <Trees_Desired.comps.1.thoughtStageDescriptions.6>樹木受蹂躪了</Trees_Desired.comps.1.thoughtStageDescriptions.6>
  <!-- EN: Trees ravaged -->
  <Trees_Desired.comps.1.thoughtStageDescriptions.7>樹木受摧殘了</Trees_Desired.comps.1.thoughtStageDescriptions.7>
  
</LanguageData>