<?xml version="1.0" encoding="UTF-8"?>
<LanguageData>

  <!-- EN: Not a mechanitor -->
  <NotAMechanitor>並非御機使</NotAMechanitor>
  <!-- EN: Not enough bandwidth -->
  <NotEnoughBandwidth>頻寬不足</NotEnoughBandwidth>
  <!-- EN: Take control of {0} -->
  <ControlMech>操控{0}</ControlMech>
  <!-- EN: Cannot control {0} -->
  <CannotControlMech>無法操控{0}</CannotControlMech>
  <!-- EN: Already controlled by {0} -->
  <CannotControlMechAlreadyControlled>已被{0}操控</CannotControlMechAlreadyControlled>
  <!-- EN: Not enough bandwidth -->
  <CannotControlMechNotEnoughBandwidth>頻寬不足</CannotControlMechNotEnoughBandwidth>
  <!-- EN: Never controllable -->
  <CannotControlMechNeverControllable>永不可操控</CannotControlMechNeverControllable>
  <!-- EN: Cannot disconnect from {0} -->
  <CannotDisconnectMech>無法與{0}斷線</CannotDisconnectMech>
  <!-- EN: Disconnect from {0} -->
  <DisconnectMech>與{0}斷線</DisconnectMech>
  <!-- EN: Permanently disassemble {0} -->
  <DisassembleMech>永久分解{0}</DisassembleMech>
  <!-- EN: Cannot permanently disassemble {0} -->
  <CannotDisassembleMech>無法永久分解{0}</CannotDisassembleMech>
  <!-- EN: Must be overseer -->
  <MustBeOverseer>必須為監督者</MustBeOverseer>
  <!-- EN: Extract -->
  <Extract>抽取</Extract>
  <!-- EN: Out of command range -->
  <OutOfCommandRange>控制範圍外</OutOfCommandRange>
  <!-- EN: Cannot go here -->
  <CannotGoOutOfRange>無法到達此處</CannotGoOutOfRange>
  <!-- EN: Must be emptied -->
  <WasteContainerFull>必須先清空</WasteContainerFull>
  <!-- EN: Cannot repair mech {0} -->
  <CannotRepairMech>無法修復{0}</CannotRepairMech>

  <!-- EN: Extract xenogerm from {PAWN_nameDef} -->
  <ExtractXenogermFrom>從{PAWN_nameDef}抽取異種基因</ExtractXenogermFrom>
  <!-- EN: Enter {0_labelShort} -->
  <EnterBuilding>進入{0_labelShort}</EnterBuilding>
  <!-- EN: {PAWN_nameDef} has no genes -->
  <PawnHasNoGenes>{PAWN_nameDef}沒有基因</PawnHasNoGenes>
  <!-- EN: {PAWN_nameDef} has no extractable genes. -->
  <PawnHasNoNonArchiteGenes>{PAWN_nameDef}沒有可抽取的基因</PawnHasNoNonArchiteGenes>
  <!-- EN: In xenogermination coma -->
  <InXenogerminationComa>正陷入異種細胞發作昏迷</InXenogerminationComa>
  <!-- EN: Occupied -->
  <Occupied>已佔用</Occupied>
  <!-- EN: {PAWN_nameDef} was ejected from a growth vat -->
  <OccupantEjectedFromGrowthVat>{PAWN_nameDef}脫離了發育艙</OccupantEjectedFromGrowthVat>
  <!-- EN: {PAWN_nameDef} must be younger than {AGEYEARS} years old. -->
  <TooOld>{PAWN_nameDef}必須少於{AGEYEARS}歲。</TooOld>
  <!-- EN: {PAWN_nameDef} is too old. -->
  <PawnIsTooOld>{PAWN_nameDef}太老了。</PawnIsTooOld>
  <!-- EN: {PAWN_nameDef} is suffering from biostarvation. -->
  <PawnBiostarving>{PAWN_nameDef}正陷入生理饑餓。</PawnBiostarving>
  <!-- EN: No available people -->
  <NoViablePawns>沒有適合的人</NoViablePawns>
  <!-- EN: No extractable people -->
  <NoExtractablePawns>沒有可抽取的人</NoExtractablePawns>
  <!-- EN: No implantable people -->
  <NoImplantablePawns>沒有可移植的人</NoImplantablePawns>
  <!-- EN: Cannot enter {0_labelShort} -->
  <CannotEnterBuilding>無法進入{0_labelShort}</CannotEnterBuilding>
  <!-- EN: {0_labelShort} is assigned to another person. -->
  <AssignedToOtherPawn>{0_labelShort}已被分配給別人。</AssignedToOtherPawn>

  <!-- EN: Absorb xenogerm of {PAWN_nameDef} -->
  <AbsorbXenogerm>從{PAWN_nameDef}吸收異種細胞</AbsorbXenogerm>
  <!-- EN: Cannot absorb {PAWN_nameDef}'s xenogerm -->
  <CannotAbsorbXenogerm>無法吸收{PAWN_nameDef}的異種細胞</CannotAbsorbXenogerm>
  <!-- EN: {PAWN_nameDef} is already {PAWN_xenotype} -->
  <SameXenotype>{PAWN_nameDef}已是{PAWN_xenotype}</SameXenotype>
  <!-- EN: {PAWN_nameDef} suffering from xenogerm loss shock -->
  <XenogermLossShockPresent>{PAWN_nameDef}陷入基因缺失休克</XenogermLossShockPresent>
  <!-- EN: Carry to {0_labelShort} -->
  <CarryToSpecificThing>帶到{0_labelShort}</CarryToSpecificThing>
  <!-- EN: No reachable, un-reserved bed or deathrest casket in safe temperature. -->
  <NoCasketOrBed>無法前往或沒有可用的床或絕息棺材。</NoCasketOrBed>
  <!-- EN: {PAWN_nameDef} is a temporary faction member. -->
  <TemporaryFactionMember>{PAWN_nameDef}是臨時派系的成員。</TemporaryFactionMember>

  <!-- EN: Scanner not initiated -->
  <SubcoreScannerNotInit>掃描儀未啟動</SubcoreScannerNotInit>
  <!-- EN: Waiting for ingredients -->
  <SubcoreScannerRequiresIngredients>等待材料</SubcoreScannerRequiresIngredients>
  <!-- EN: Occupied -->
  <SubcoreScannerOccupied>已佔用</SubcoreScannerOccupied>
  <!-- EN: Enter {0} -->
  <EnterSubcoreScanner>進入{0}</EnterSubcoreScanner>

  <!-- EN: Breastfeed {BABY_labelShort} -->
  <BabyCareBreastfeed>母乳喂哺{BABY_labelShort}</BabyCareBreastfeed>
  <!-- EN: Cannot breastfeed {BABY_labelShort} -->
  <BabyCareBreastfeedUnable>無法喂哺{BABY_labelShort}</BabyCareBreastfeedUnable>
  <!-- EN: Already breastfeeding {BABY_labelShort} -->
  <AlreadyBreastfeeding>已在喂哺{BABY_labelShort}</AlreadyBreastfeeding>
  <!-- EN: No baby-edible food -->
  <NoBabyFood>沒有嬰兒食品</NoBabyFood>

  <!-- EN: play need full -->
  <CannotInteractBabyPlayFull>遊玩需求已滿</CannotInteractBabyPlayFull>

  <!-- EN: Feed on {PAWN_nameDef} -->
  <BloodfeedOn>吸{PAWN_nameDef}的血</BloodfeedOn>
  <!-- EN: Cannot feed on {PAWN_nameDef} -->
  <CannotBloodfeedOn>無法吸{PAWN_nameDef}的血</CannotBloodfeedOn>
  <!-- EN: Not enough blood. -->
  <CannotFeedOnWouldKill>血量不足。</CannotFeedOnWouldKill>

  <!-- BreastfeedFailReason strings-->
  <!-- EN: {MOM_labelShort} does not have enough milk -->
  <BreastfeedFailReason_MomNotEnoughMilk>{MOM_labelShort}母乳量不足</BreastfeedFailReason_MomNotEnoughMilk>
  <!-- EN: {MOM_labelShort} cannot breastfeed right now -->
  <BreastfeedFailReason_MomInMentalState>{MOM_labelShort}目前無法喂哺</BreastfeedFailReason_MomInMentalState>
  <!-- EN: {BABY_labelShort} is too full to suckle -->
  <BreastfeedFailReason_BabyTooFull>{BABY_labelShort}飽到喝不下了</BreastfeedFailReason_BabyTooFull>
  <!-- EN: {BABY_labelShort} is forbidden to {MOM_labelShort} -->
  <BreastfeedFailReason_BabyForbiddenToMom>{BABY_labelShort}被禁止與{MOM_labelShort}接觸</BreastfeedFailReason_BabyForbiddenToMom>
  <!-- EN: {BABY_labelShort} is forbidden to {HAULER_labelShort} -->
  <BreastfeedFailReason_BabyForbiddenToHauler>{BABY_labelShort}被禁止與{HAULER_labelShort}接觸</BreastfeedFailReason_BabyForbiddenToHauler>
  <!-- EN: {MOM_labelShort} is forbidden to {HAULER_labelShort} -->
  <BreastfeedFailReason_MomForbiddenToHauler>{MOM_labelShort}被禁止與{HAULER_labelShort}接觸</BreastfeedFailReason_MomForbiddenToHauler>
  <!-- EN: {MOM_labelShort} can breastfeed {BABY_labelShort} without help -->
  <BreastfeedFailReason_MomIsMobile>{MOM_labelShort}無法獨自喂哺{BABY_labelShort}</BreastfeedFailReason_MomIsMobile>
  <!-- EN: {HAULER_labelShort} cannot go from {BABY_labelShort} to {MOM_labelShort} -->
  <BreastfeedFailReason_HaulerCannotReachMom>{HAULER_labelShort}無法從{BABY_labelShort}走到{MOM_labelShort}</BreastfeedFailReason_HaulerCannotReachMom>
  <!-- EN: {HAULER_labelShort} cannot reach {BABY_labelShort} -->
  <BreastfeedFailReason_HaulerCannotReachBaby>{HAULER_labelShort}無法接觸{BABY_labelShort}</BreastfeedFailReason_HaulerCannotReachBaby>
  <!-- EN: No lactating {BABY_factionPawnsPlural} are assigned to {BABY_labelShort} -->
  <BreastfeedFailReason_NoMomsAssignedToBaby>沒有泌乳中的{BABY_factionPawnsPlural}分配給{BABY_labelShort}</BreastfeedFailReason_NoMomsAssignedToBaby>
  <!-- EN: {MOM_labelShort} is not assigned to childcare -->
  <BreastfeedFailReason_MomNotAssignedToChildcare>{MOM_labelShort}未被指派育兒工作</BreastfeedFailReason_MomNotAssignedToChildcare>
  <!-- EN: {MOM_labelShort} is inside a container -->
  <BreastfeedFailReason_MomInsideContainer>{MOM_labelShort}身處容器之中</BreastfeedFailReason_MomInsideContainer>
  <!-- EN: {MOM_labelShort} is being carried -->
  <BreastfeedFailReason_MomBeingCarried>{MOM_labelShort}正被帶著走</BreastfeedFailReason_MomBeingCarried>

  <!-- EN: Order implantation into {PAWN_nameDef} -->
  <OrderImplantationIntoPawn>為{PAWN_nameDef}預約移植</OrderImplantationIntoPawn>
  <!-- EN: Accept {0_xenotype} xenogerm -->
  <AcceptXenogerm>接受{0_xenotype}異種細胞</AcceptXenogerm>

  <!-- EN: Carry {PAWN_labelShort} to recharger -->
  <CarryToRechargerOrdered>帶{PAWN_labelShort}到充電站</CarryToRechargerOrdered>
  <!-- EN: Cannot carry {PAWN_labelShort} to recharger -->
  <CannotCarryToRecharger>無法帶{PAWN_labelShort}到充電站</CannotCarryToRecharger>
  <!-- EN: No available recharger -->
  <CannotCarryToRechargerNoneAvailable>沒有可用的充電站</CannotCarryToRechargerNoneAvailable>

  <!-- EN: Hemogen packs disabled by food restriction. -->
  <NotAllowedHemogen>血原包受客製化菜單禁止。</NotAllowedHemogen>

  <!-- EN: Eject genepack from gene bank -->
  <EjectGenepackFromGeneBank>從基因庫中退出基因包</EjectGenepackFromGeneBank>

  <!-- EN: Resulting metabolism would be too low -->
  <ResultingMetTooLow>可能導致新陳代謝過低</ResultingMetTooLow>

  <!-- EN: attempted romance too recently -->
  <RomanceOnCooldown>離上次試圖約會不久</RomanceOnCooldown>

  <!-- EN: Take to safe location -->
  <CarryToSafePlace>帶到安全地點</CarryToSafePlace>
  <!-- EN: Cannot take to safe location -->
  <CannotCarryToSafePlace>無法帶到安全地點</CannotCarryToSafePlace>
  <!-- EN: No safer location than current location -->
  <NoBetterSafePlace>沒有比目前更安全的地點</NoBetterSafePlace>
  <!-- EN: Already taking to safe location -->
  <AlreadyCarryingToSafePlace>已經正在帶到安全地點</AlreadyCarryingToSafePlace>

  <!-- UNUSED -->
  <CannotStudy>無法研究</CannotStudy>
  <AlreadyStudied>已經研究</AlreadyStudied>

</LanguageData>