<?xml version="1.0" encoding="UTF-8"?>
<LanguageData>
  
  <!-- EN: install blood warmer -->
  <InstallBloodWarmer.label>安裝血液加溫器</InstallBloodWarmer.label>
  <!-- EN: Install blood warmer. -->
  <InstallBloodWarmer.description>安裝血液加溫器。</InstallBloodWarmer.description>
  <!-- EN: Installing blood warmer. -->
  <InstallBloodWarmer.jobString>正在安裝血液加溫器。</InstallBloodWarmer.jobString>
  
  <!-- EN: install pilot assistant -->
  <InstallPilotAssistant.label>安裝駕駛助手</InstallPilotAssistant.label>
  <!-- EN: Install a pilot assistant. -->
  <InstallPilotAssistant.description>安裝駕駛助手。</InstallPilotAssistant.description>
  <!-- EN: Installing pilot assistant. -->
  <InstallPilotAssistant.jobString>正在安裝駕駛助手。</InstallPilotAssistant.jobString>
  
  <!-- EN: install vacskin gland -->
  <InstallVacskinGland.label>植入蠟膚腺體</InstallVacskinGland.label>
  <!-- EN: Install a vacskin gland. -->
  <InstallVacskinGland.description>植入蠟膚腺體。</InstallVacskinGland.description>
  <!-- EN: Installing vacskin gland. -->
  <InstallVacskinGland.jobString>正在植入蠟膚腺體。</InstallVacskinGland.jobString>
  
  <!-- EN: remove pilot assistant -->
  <RemovePilotAssistant.label>移除駕駛助手</RemovePilotAssistant.label>
  <!-- EN: Remove pilot assistant. -->
  <RemovePilotAssistant.description>移除駕駛助手。</RemovePilotAssistant.description>
  <!-- EN: Removing pilot assistant. -->
  <RemovePilotAssistant.jobString>正在移除駕駛助手。</RemovePilotAssistant.jobString>
  
  <!-- EN: remove vacskin gland -->
  <RemoveVacskinGland.label>摘除蠟膚腺體</RemoveVacskinGland.label>
  <!-- EN: Remove vacskin gland. -->
  <RemoveVacskinGland.description>摘除蠟膚腺體。</RemoveVacskinGland.description>
  <!-- EN: Removing vacskin gland. -->
  <RemoveVacskinGland.jobString>正在摘除蠟膚腺體。</RemoveVacskinGland.jobString>
  
</LanguageData>