<?xml version="1.0" encoding="UTF-8"?>
<LanguageData>
  
  <!-- EN: blood rain -->
  <BloodRain.label>血雨</BloodRain.label>
  <!-- EN: Blood rain -->
  <BloodRain.letterLabel>血雨</BloodRain.letterLabel>
  
  <!-- EN: creepjoiner join -->
  <CreepJoinerJoin.label>詭異避難者加入</CreepJoinerJoin.label>
  
  <!-- EN: creepjoiner join -->
  <CreepJoinerJoin_Metalhorror.label>詭異避難者加入</CreepJoinerJoin_Metalhorror.label>
  
  <!-- EN: death pall -->
  <DeathPall.label>死亡之霧</DeathPall.label>
  <!-- EN: Death pall -->
  <DeathPall.letterLabel>死亡之霧</DeathPall.letterLabel>
  
  <!-- EN: fleshmass heart -->
  <FleshmassHeart.label>血肉團心臟</FleshmassHeart.label>
  <!-- EN: Something from below -->
  <FleshmassHeart.letterLabel>來自地下的東西</FleshmassHeart.letterLabel>
  <!-- EN: A small circle of terrain has begun to shift and crack apart. Something is digging up towards the surface. Rhythmic pulsations shake the ground from underneath. -->
  <FleshmassHeart.letterText>一小圈地帶開始移動並裂開。有東西正朝地表挖掘。地面下有節奏的脈動搖晃著地面。</FleshmassHeart.letterText>
  
  <!-- EN: distress signal -->
  <GiveQuest_DistressCall.label>求救信號</GiveQuest_DistressCall.label>
  <!-- EN: Distress signal -->
  <GiveQuest_DistressCall.letterLabel>求救信號</GiveQuest_DistressCall.letterLabel>
  
  <!-- EN: golden cube arrival -->
  <GoldenCubeArrival.label>黃金立方體抵達</GoldenCubeArrival.label>
  
  <!-- EN: metalhorror implantation -->
  <MetalhorrorImplantation.label>懼金移植</MetalhorrorImplantation.label>
  
  <!-- EN: mysterious cargo cube -->
  <MysteriousCargoCube.label>神祕貨物立方體</MysteriousCargoCube.label>
  
  <!-- EN: mysterious cargo revenant spine -->
  <MysteriousCargoRevenantSpine.label>神祕貨物亡魂脊椎</MysteriousCargoRevenantSpine.label>
  
  <!-- EN: mysterious cargo corpse -->
  <MysteriousCargoUnnaturalCorpse.label>神祕貨物屍體</MysteriousCargoUnnaturalCorpse.label>
  
  <!-- EN: nociosphere -->
  <Nociosphere.label>知性球體</Nociosphere.label>
  <!-- EN: Nociosphere -->
  <Nociosphere.letterLabel>知性球體</Nociosphere.letterLabel>
  <!-- EN: A strange metallic sphere has appeared. It hurts to be near it.\n\nYou could attack it, though you're not sure how it might defend itself. Or, you could capture it using a holding platform and learn to make use of its power.\n\nIt seems quiet for now, but it is gaining energy over time. You can suppress the sphere when it is captured to a holding platform, reducing its energy. -->
  <Nociosphere.letterText>一個奇怪的金屬球出現了。靠近它會感到疼痛。\n\n你可以對它進行攻擊，雖然你不確定它會如何反擊。或者，你可以使用收容平台捕捉它，學會如何利用它的力量。\n\n它暫時看起來很平靜，但它正隨著時間獲得能量。當球體被捕獲到收容平台時，你可以對它進行抑制，以減少它的能量。</Nociosphere.letterText>
  
  <!-- EN: pit gate -->
  <PitGate.label>大坑洞</PitGate.label>
  <!-- EN: Pit gate opening -->
  <PitGate.letterLabel>大坑洞開口</PitGate.letterLabel>
  <!-- EN: A wide piece of terrain has begun sinking into the depths, forming a deepening hole. At this rate, it will deepen out of sight within a day. You can hear inhuman shrieks rising from the depths.\n\nMove buildings and items away from the emergence point. -->
  <PitGate.letterText>一片寬闊的地帶開始朝深處下沉，形成一個逐漸加深的洞。照這個速度，它會在一天之內深不見底。你可以聽到從深處傳來的非人叫聲。\n\n將建築物和物品從出現點移開。</PitGate.letterText>
  
  <!-- EN: revenant emergence -->
  <RevenantEmergence.label>亡魂現身</RevenantEmergence.label>
  <!-- EN: Revenant spine humming -->
  <RevenantEmergence.letterLabel>亡魂脊椎嗡鳴</RevenantEmergence.letterLabel>
  <!-- EN: The revenant spine is becoming more active and emitting an ominous hum. Destroy it or restrain it on a holding platform before it's too late. -->
  <RevenantEmergence.letterText>亡魂脊椎變得越來越活躍，並發出不祥的嗡鳴聲。趁現在還來得及，摧毀它或將其限制在收容平台上。</RevenantEmergence.letterText>
  
  <!-- EN: unnatural corpse arrival -->
  <UnnaturalCorpseArrival.label>不自然的屍體抵達</UnnaturalCorpseArrival.label>
  
  <!-- EN: unnatural darkness -->
  <UnnaturalDarkness.label>不自然的黑暗</UnnaturalDarkness.label>
  
  <!-- EN: warped obelisk -->
  <WarpedObelisk_Abductor.label>變形方尖碑</WarpedObelisk_Abductor.label>
  <!-- EN: Warped obelisk -->
  <WarpedObelisk_Abductor.letterLabel>變形方尖碑</WarpedObelisk_Abductor.letterLabel>
  <!-- EN: A mysterious obelisk has crashed nearby.\n\nThe obelisk hums with putrid psychic energy, gradually intensifying as it approaches some dangerous limit. You can send colonists to suppress the obelisk to prevent it from activating.\n\nYou can also mark the obelisk for study to try to learn its purpose and perhaps make use of it.\n\nYou can always attack the obelisk to destroy it, but doing so may unleash unnatural and dangerous phenomena. -->
  <WarpedObelisk_Abductor.letterText>一座神祕的方尖碑在附近墜毀。\n\n方尖碑嗡鳴著腐爛的心靈能量，逐漸加劇著，不斷接近某種危險的極限。你可以派遣殖民者來抑制方尖碑，防止它啟動。\n\n你也可以標記方尖碑以進行研究，嘗試瞭解其用途並加以利用。\n\n你隨時可以攻擊方尖碑摧毀它，但這樣可能會引發非自然和危險的現象。</WarpedObelisk_Abductor.letterText>
  
  <!-- EN: corrupted obelisk -->
  <WarpedObelisk_Duplicator.label>腐化方尖碑</WarpedObelisk_Duplicator.label>
  <!-- EN: Corrupted obelisk -->
  <WarpedObelisk_Duplicator.letterLabel>腐化方尖碑</WarpedObelisk_Duplicator.letterLabel>
  <!-- EN: A mysterious obelisk has crashed nearby.\n\nThe obelisk hums with putrid psychic energy, gradually intensifying as it approaches some dangerous limit. You can send colonists to suppress the obelisk to prevent it from activating.\n\nYou can also mark the obelisk for study to try to learn its purpose and perhaps make use of it.\n\nYou can always attack the obelisk to destroy it, but doing so may unleash unnatural and dangerous phenomena. -->
  <WarpedObelisk_Duplicator.letterText>一座神祕的方尖碑在附近墜毀。\n\n方尖碑嗡鳴著腐爛的心靈能量，逐漸加劇著，不斷接近某種危險的極限。你可以派遣殖民者來抑制方尖碑，防止它啟動。\n\n你也可以標記方尖碑以進行研究，嘗試瞭解其用途並加以利用。\n\n你隨時可以攻擊方尖碑摧毀它，但這樣可能會引發非自然和危險的現象。</WarpedObelisk_Duplicator.letterText>
  
  <!-- EN: twisted obelisk -->
  <WarpedObelisk_Mutator.label>扭曲方尖碑</WarpedObelisk_Mutator.label>
  <!-- EN: Twisted obelisk -->
  <WarpedObelisk_Mutator.letterLabel>扭曲方尖碑</WarpedObelisk_Mutator.letterLabel>
  <!-- EN: A mysterious obelisk has crashed nearby.\n\nThe obelisk hums with putrid psychic energy, gradually intensifying as it approaches some dangerous limit. You can send colonists to suppress the obelisk to prevent it from activating.\n\nYou can also mark the obelisk for study to try to learn its purpose and perhaps make use of it.\n\nYou can always attack the obelisk to destroy it, but doing so may unleash unnatural and dangerous phenomena. -->
  <WarpedObelisk_Mutator.letterText>一座神祕的方尖碑在附近墜毀。\n\n方尖碑嗡鳴著腐爛的心靈能量，逐漸加劇著，不斷接近某種危險的極限。你可以派遣殖民者來抑制方尖碑，防止它啟動。\n\n你也可以標記方尖碑以進行研究，嘗試瞭解其用途並加以利用。\n\n你隨時可以攻擊方尖碑摧毀它，但這樣可能會引發非自然和危險的現象。</WarpedObelisk_Mutator.letterText>
  
</LanguageData>