<?xml version="1.0" encoding="utf-8" ?>
<LanguageData>
		
        <ShipBasics.label>基本星艦建造</ShipBasics.label>
        <ShipBasics.description>允許你研究更多關於建造星艦的科技以建造一艘逃離這個星球的星艦。</ShipBasics.description>
		
		<ShipCryptosleep.label>星艦休眠艙</ShipCryptosleep.label>
        <ShipCryptosleep.description>允许你建造用於星際旅行的休眠艙。</ShipCryptosleep.description>
		
		<ShipReactor.label>反物質星艦反應堆</ShipReactor.label>
        <ShipReactor.description>允許你使用反物質牽制核心來建造一個可以驅動整艘星艦的反應堆。</ShipReactor.description>
		
		<ShipEngine.label>反物質星艦推進</ShipEngine.label>
        <ShipEngine.description>允許你使用反物質牽制核心來建造一個反物質推進器。</ShipEngine.description>
		
		<ShipComputerCore.label>星艦電腦核心</ShipComputerCore.label>
        <ShipComputerCore.description>允許你將一個已經存在的AI系統裝入一個用於導航星艦的電腦核心裡。</ShipComputerCore.description>
 
</LanguageData>