<?xml version="1.0" encoding="utf-8"?>
<LanguageData>
  
  <!-- Misc -->
  
  <Body.label>身體</Body.label>
  <Beak.label>鳥喙</Beak.label>
  <InsectHead.label>頭部</InsectHead.label>
  <SnakeBody.label>蛇身</SnakeBody.label>
  <SnakeHead.label>蛇頭</SnakeHead.label>
  <SnakeMouth.label>蛇吻</SnakeMouth.label>
  <InsectHeart.label>昆蟲心臟</InsectHeart.label>
  <InsectNostril.label>鼻孔</InsectNostril.label>
  <InsectMouth.label>蟲口</InsectMouth.label>
  <AnimalJaw.label>下顎</AnimalJaw.label>
  <Jowl.label>臉頰</Jowl.label>
  <Tail.label>尾巴</Tail.label>
  <Antenna.label>觸鬚</Antenna.label>
  <Pronotum.label>前胸</Pronotum.label>
  <Shell.label>外殼</Shell.label>
  <Elytra.label>翅鞘</Elytra.label>
  <Tusk.label>長牙</Tusk.label>
  <Trunk.label>象鼻</Trunk.label>
  <Horn.label>角</Horn.label>
  <HeadClaw.label>頭爪</HeadClaw.label>
  <Hump.label>駝峰</Hump.label>
  <TurtleShell.label>龜殼</TurtleShell.label>
  <Plastron.label>腹甲</Plastron.label>
  <TurtleBeak.label>龜喙</TurtleBeak.label>


  <!-- Insect legs -->

  <InsectLeg.label>蟲腳</InsectLeg.label>


  <!-- Paws -->

  <Paw.label>掌</Paw.label>


  <!-- Hoofs -->

  <Hoof.label>蹄</Hoof.label>


  <!-- Claws -->

  <FrontClaw.label>前爪</FrontClaw.label>
  <FrontClaw.labelShort>爪</FrontClaw.labelShort>

  <RearClaw.label>後爪</RearClaw.label>
  <RearClaw.labelShort>爪</RearClaw.labelShort>
  
  
</LanguageData>
